delite/__init__.py
delite/connection.py
delite/credentials.py
delite/sql.py
delite/storage.py
delite-0.0.10rc1.dist-info/METADATA
delite-0.0.10rc1.dist-info/WHEEL
delite-0.0.10rc1.dist-info/RECORD
